spur/__init__.py
spur/errors.py
spur/files.py
spur/io.py
spur/local.py
spur/results.py
spur/ssh.py
spur/tempdir.py
spur-0.3.23.dist-info/LICENSE
spur-0.3.23.dist-info/METADATA
spur-0.3.23.dist-info/WHEEL
spur-0.3.23.dist-info/top_level.txt
spur-0.3.23.dist-info/RECORD
