Metadata-Version: 2.1
Name: spur
Version: 0.3.23
Summary: Run commands and manipulate files locally or over SSH using the same interface
Home-page: https://github.com/mwilliamson/spur.py
Author: Michael Williamson
Author-email: mike@zwobble.org
License: BSD-2-Clause
Keywords: ssh shell subprocess process
Classifier: Development Status :: 4 - Beta
Classifier: Intended Audience :: Developers
Classifier: License :: OSI Approved :: BSD License
Classifier: Programming Language :: Python
Classifier: Programming Language :: Python :: 3
Classifier: Programming Language :: Python :: 3.6
Classifier: Programming Language :: Python :: 3.7
Classifier: Programming Language :: Python :: 3.8
Classifier: Programming Language :: Python :: 3.9
Classifier: Programming Language :: Python :: 3.10
Classifier: Programming Language :: Python :: 3.11
Classifier: Topic :: Internet
Requires-Python: >=3.6
License-File: LICENSE
